LICENSE
MANIFEST.in
README.md
setup.py
django_notifications/__init__.py
django_notifications/apps.py
django_notifications/helpers.py
django_notifications/models.py
django_notifications/tests.py
django_notifications/migrations/0001_initial.py
django_notifications/migrations/0002_notificationqueue_send_after.py
django_notifications/migrations/__init__.py
django_notifications2.egg-info/PKG-INFO
django_notifications2.egg-info/SOURCES.txt
django_notifications2.egg-info/dependency_links.txt
django_notifications2.egg-info/top_level.txt